README.md
setup.py
panshell/__init__.py
panshell/base.py
panshell/core.py
panshell/main.py
panshell.egg-info/PKG-INFO
panshell.egg-info/SOURCES.txt
panshell.egg-info/dependency_links.txt
panshell.egg-info/entry_points.txt
panshell.egg-info/top_level.txt
panshell/baidu/__init__.py
panshell/baidu/account.py
panshell/baidu/pan.py
panshell/local/__init__.py