Metadata-Version: 1.0
Name: panshell
Version: 0.0.3a0
Summary: shell for baidu yunpan
Home-page: UNKNOWN
Author: alingse
Author-email: alingse@foxmail.com
License:                                  Apache License
